warn_dependents/__about__.py
warn_dependents/__init__.py
warn_dependents/__main__.py
warn_dependents/api.py
warn_dependents/cli.py
warn_dependents/core.py
warn_dependents-0.0.2.dist-info/METADATA
warn_dependents-0.0.2.dist-info/WHEEL
warn_dependents-0.0.2.dist-info/entry_points.txt
warn_dependents-0.0.2.dist-info/licenses/LICENSE.txt
warn_dependents-0.0.2.dist-info/RECORD
