Metadata-Version: 2.4
Name: warn-dependents
Version: 0.0.2
Summary: Email the authors and maintainers of all projects using a PyPi project (e.g. yours) downstream.  By default, warn them it is intended to drop support for old Python versions.
Project-URL: Issues, https://github.com/JamesParrott/warn-dependents/issues
Project-URL: Source, https://github.com/JamesParrott/warn-dependents
Author-email: JamesParrott <james.parrott@proton.me>
License-Expression: AGPL-3.0-or-later
License-File: LICENSE.txt
Classifier: Development Status :: 4 - Beta
Classifier: Programming Language :: Python
Classifier: Programming Language :: Python :: 3.9
Classifier: Programming Language :: Python :: 3.10
Classifier: Programming Language :: Python :: 3.11
Classifier: Programming Language :: Python :: 3.12
Classifier: Programming Language :: Python :: Implementation :: CPython
Classifier: Programming Language :: Python :: Implementation :: PyPy
Requires-Python: >=3.12
Requires-Dist: maintainers-and-authors
Requires-Dist: nameutils
Requires-Dist: requests
Requires-Dist: sparkpost
